rgb_stat/__init__.py
rgb_stat/image_util.py
rgb_stat/main.py
rgb_stat/stat.py
rgb_stat/util.py
rgb_stat-1.0.1.dist-info/LICENSE
rgb_stat-1.0.1.dist-info/METADATA
rgb_stat-1.0.1.dist-info/WHEEL
rgb_stat-1.0.1.dist-info/entry_points.txt
rgb_stat-1.0.1.dist-info/top_level.txt
rgb_stat-1.0.1.dist-info/RECORD
